{
    "assets": {
        "image_geotiff": {
            "href": "image_geotiff.tif",
            "type": "image/tiff; application=geotiff"
        },
        "image_jpeg": {
            "href": "image_jpeg.jpg",
            "type": "image/jpeg"
        }
    },
    "bbox": [
        -87.5994873046875,
        15.919073517982426,
        -87.593994140625,
        15.9243559500513
    ],
    "collection": "nasa_marine_debris_source",
    "geometry": {
        "coordinates": [
            [
                [
                    -87.5994873046875,
                    15.9243559500513
                ],
                [
                    -87.5994873046875,
                    15.919073517982426
                ],
                [
                    -87.593994140625,
                    15.919073517982426
                ],
                [
                    -87.593994140625,
                    15.9243559500513
                ],
                [
                    -87.5994873046875,
                    15.9243559500513
                ]
            ]
        ],
        "type": "Polygon"
    },
    "id": "nasa_marine_debris_source_20161008_153104_0e3a_16821-29831-16",
    "links": [
        {
            "href": "../collection.json",
            "rel": "collection"
        },
        {
            "href": "../collection.json",
            "rel": "parent"
        }
    ],
    "properties": {
        "datetime": "2016-10-08T00:00:00Z"
    },
    "stac_extensions": [
        "https://stac-extensions.github.io/eo/v1.0.0/schema.json"
    ],
    "stac_version": "1.0.0",
    "type": "Feature"
}